ruv_dl/__init__.py
ruv_dl/cache.py
ruv_dl/constants.py
ruv_dl/crawler.py
ruv_dl/data.py
ruv_dl/date_utils.py
ruv_dl/downloader.py
ruv_dl/exceptions.py
ruv_dl/mover.py
ruv_dl/programs.py
ruv_dl/runtime.py
ruv_dl/migrations/__init__.py
tests/__init__.py
tests/test_actions.py
tests/test_data.py
tests/test_mover.py
tests/test_runtime.py
ruv_dl-0.5.4.dist-info/LICENSE
ruv_dl-0.5.4.dist-info/METADATA
ruv_dl-0.5.4.dist-info/WHEEL
ruv_dl-0.5.4.dist-info/entry_points.txt
ruv_dl-0.5.4.dist-info/top_level.txt
ruv_dl-0.5.4.dist-info/RECORD
