Metadata-Version: 2.1
Name: ruv-dl
Version: 0.5.4
Summary: Downloader/organizer for ruv programs
Home-page: https://github.com/sindrig/ruv-dl
Author: Sindri Guðmundsson
Author-email: sindrigudmundsson@gmail.com
License: MIT
Platform: UNKNOWN
Classifier: License :: OSI Approved :: MIT License
Classifier: Development Status :: 4 - Beta
Classifier: Environment :: Console
Classifier: Programming Language :: Python
Classifier: Programming Language :: Python :: 3
Classifier: Programming Language :: Python :: 3 :: Only
Classifier: Programming Language :: Python :: 3.6
Classifier: Programming Language :: Python :: Implementation :: CPython
Requires-Python: >=3.6.0
Requires-Dist: requests (==2.22.0)
Requires-Dist: click (==7.0)
